zerohertzPkg/__init__.py
zerohertzPkg-0.2.dist-info/METADATA
zerohertzPkg-0.2.dist-info/WHEEL
zerohertzPkg-0.2.dist-info/top_level.txt
zerohertzPkg-0.2.dist-info/RECORD
