Metadata-Version: 2.1
Name: zerohertzPkg
Version: 0.2
Summary: Zerohertz's Library
Home-page: UNKNOWN
Author: Zerohertz
License: UNKNOWN
Platform: UNKNOWN
Requires-Python: >=3.7.0
